<?xml version="1.0" encoding="windows-1252" ?>
<TODOLIST FILENAME="C:\Users\master\Work\sqlt.17\SQLTools\ToDo-SQLTools-1.7.xml" PROJECTNAME="" FILEFORMAT="9" NEXTUNIQUEID="115" LASTMODIFIED="2014-07-04" FILEVERSION="132" EARLIESTDUEDATE="0.00000000">
<TASK TITLE="New" ID="102" ICONINDEX="-1" POS="1" PRIORITY="5" RISK="0" PERCENTDONE="0" COST="0.00000000" CALCCOST="0.00000000" STARTDATE="41824.00000000" STARTDATESTRING="2014-07-04" CREATIONDATE="41824.95582176" CREATIONDATESTRING="2014-07-04T22:56" LASTMOD="41824.95592593" LASTMODSTRING="2014-07-04T22:56" PRIORITYCOLOR="15732480" PRIORITYWEBCOLOR="#000FF0">
<TASK TITLE="1" ID="103" ICONINDEX="-1" COMMENTS="save and open session from &quot;Open Files&quot;
save with bookmarks and cursor positions

" POS="1" PRIORITY="5" RISK="0" PERCENTDONE="0" COST="0.00000000" CALCCOST="0.00000000" STARTDATE="41824.00000000" STARTDATESTRING="2014-07-04" CREATIONDATE="41824.95603009" CREATIONDATESTRING="2014-07-04T22:56" LASTMOD="41824.95666667" LASTMODSTRING="2014-07-04T22:57" COMMENTSTYPE="PLAIN_TEXT" PRIORITYCOLOR="15732480" PRIORITYWEBCOLOR="#000FF0"/>
<TASK TITLE="2" ID="104" ICONINDEX="-1" COMMENTS="i forgot to add query and count to menu. also sql popup menu" POS="2" PRIORITY="5" RISK="0" PERCENTDONE="0" COST="0.00000000" CALCCOST="0.00000000" STARTDATE="41824.00000000" STARTDATESTRING="2014-07-04" CREATIONDATE="41824.95711806" CREATIONDATESTRING="2014-07-04T22:58" LASTMOD="41824.95730324" LASTMODSTRING="2014-07-04T22:58" COMMENTSTYPE="PLAIN_TEXT" PRIORITYCOLOR="15732480" PRIORITYWEBCOLOR="#000FF0"/>
<TASK TITLE="3. more info in ObjectViewer infotips" ID="105" ICONINDEX="-1" COMMENTS="It is nice that a hover-window appears when your mouse is going over an index name. Wouldn’t it be better that the field “Type” would match the index type? In fact the index in the screenshot below is an Oracle Text index (index_type = DOMAIN in select index_type from user_indexes) but it just says “INDEX” in the screenshot

- Also useful fields to show for indexes are: UNIQUENESS, TABLESPACE_NAME, STATUS, VISIBILITY (11.2 or higher), DEGREE, PARTITIONED. I assume you are doing the query on all_indexes anyway, so adding these fields might be easy.

- Same for constraints: STATUS, DELETE_RULE (from all_constraints)

-  Same for the table itself: NUM_ROWS, DEGREE, LAST_ANALYZED, PARTITIONED, TEMPORARY, COMPRESS_FOR (these are the most common columns I think), optionally: BLOCKS*&lt;tablespace-block_size&gt;" POS="3" PRIORITY="5" RISK="0" PERCENTDONE="0" COST="0.00000000" CALCCOST="0.00000000" STARTDATE="41824.00000000" STARTDATESTRING="2014-07-04" CREATIONDATE="41824.95943287" CREATIONDATESTRING="2014-07-04T23:01" LASTMOD="41824.96015046" LASTMODSTRING="2014-07-04T23:02" COMMENTSTYPE="PLAIN_TEXT" PRIORITYCOLOR="15732480" PRIORITYWEBCOLOR="#000FF0"/>
<TASK TITLE="4. autocomplete" ID="106" ICONINDEX="-1" COMMENTS="- In the auto-complete for tables, I would limit the list of tables to only those that match what you have typed already. So in this screenshot:

The list should only contain the tables that start with “hdt_c…” and not hdt_billing_user_rates etc…
" POS="4" PRIORITY="5" RISK="0" PERCENTDONE="0" COST="0.00000000" CALCCOST="0.00000000" STARTDATE="41824.00000000" STARTDATESTRING="2014-07-04" CREATIONDATE="41824.96077546" CREATIONDATESTRING="2014-07-04T23:03" LASTMOD="41824.96103009" LASTMODSTRING="2014-07-04T23:03" COMMENTSTYPE="PLAIN_TEXT" PRIORITYCOLOR="15732480" PRIORITYWEBCOLOR="#000FF0"/>
<TASK TITLE="5. Possibility to select the ORACLE_HOME to be used for finding the oci.dll" ID="107" ICONINDEX="-1" POS="5" PRIORITY="5" RISK="0" PERCENTDONE="0" COST="0.00000000" CALCCOST="0.00000000" STARTDATE="41824.00000000" STARTDATESTRING="2014-07-04" CREATIONDATE="41824.96197917" CREATIONDATESTRING="2014-07-04T23:05" LASTMOD="41824.96229167" LASTMODSTRING="2014-07-04T23:05" PRIORITYCOLOR="15732480" PRIORITYWEBCOLOR="#000FF0"/>
<TASK TITLE="6. And of course ‘auto format sql’" ID="108" ICONINDEX="-1" POS="6" PRIORITY="5" RISK="0" PERCENTDONE="0" COST="0.00000000" CALCCOST="0.00000000" STARTDATE="41824.00000000" STARTDATESTRING="2014-07-04" CREATIONDATE="41824.96285880" CREATIONDATESTRING="2014-07-04T23:06" LASTMOD="41824.96321759" LASTMODSTRING="2014-07-04T23:07" PRIORITYCOLOR="15732480" PRIORITYWEBCOLOR="#000FF0"/>
<TASK TITLE="7. ‘async query (in background)’" ID="109" ICONINDEX="-1" POS="7" PRIORITY="5" RISK="0" PERCENTDONE="0" COST="0.00000000" CALCCOST="0.00000000" STARTDATE="41824.00000000" STARTDATESTRING="2014-07-04" CREATIONDATE="41824.96321759" CREATIONDATESTRING="2014-07-04T23:07" LASTMOD="41824.96333333" LASTMODSTRING="2014-07-04T23:07" PRIORITYCOLOR="15732480" PRIORITYWEBCOLOR="#000FF0"/>
<TASK TITLE="8. add 2 subst variables _sid and _serial#" ID="110" ICONINDEX="-1" POS="8" PRIORITY="5" RISK="0" PERCENTDONE="0" COST="0.00000000" CALCCOST="0.00000000" STARTDATE="41824.00000000" STARTDATESTRING="2014-07-04" CREATIONDATE="41824.96548611" CREATIONDATESTRING="2014-07-04T23:10" LASTMOD="41824.96584491" LASTMODSTRING="2014-07-04T23:10" PRIORITYCOLOR="15732480" PRIORITYWEBCOLOR="#000FF0"/>
<TASK TITLE="9. external tables" ID="111" ICONINDEX="-1" POS="9" PRIORITY="5" RISK="0" PERCENTDONE="0" COST="0.00000000" CALCCOST="0.00000000" STARTDATE="41824.00000000" STARTDATESTRING="2014-07-04" CREATIONDATE="41824.96613426" CREATIONDATESTRING="2014-07-04T23:11" LASTMOD="41824.96626157" LASTMODSTRING="2014-07-04T23:11" PRIORITYCOLOR="15732480" PRIORITYWEBCOLOR="#000FF0"/>
<TASK TITLE="10. add option to close the current cursor after N inactive minutes" ID="112" ICONINDEX="-1" POS="10" PRIORITY="5" RISK="0" PERCENTDONE="0" COST="0.00000000" CALCCOST="0.00000000" STARTDATE="41824.00000000" STARTDATESTRING="2014-07-04" CREATIONDATE="41824.96660880" CREATIONDATESTRING="2014-07-04T23:11" LASTMOD="41824.96665509" LASTMODSTRING="2014-07-04T23:11" PRIORITYCOLOR="15732480" PRIORITYWEBCOLOR="#000FF0"/>
<TASK TITLE="11. add right aliment for subpart templates/ partitions and subpartitions" ID="113" ICONINDEX="-1" POS="11" PRIORITY="5" RISK="0" PERCENTDONE="0" COST="0.00000000" CALCCOST="0.00000000" STARTDATE="41824.00000000" STARTDATESTRING="2014-07-04" CREATIONDATE="41824.96709491" CREATIONDATESTRING="2014-07-04T23:12" LASTMOD="41824.96724537" LASTMODSTRING="2014-07-04T23:12" PRIORITYCOLOR="15732480" PRIORITYWEBCOLOR="#000FF0"/>
<TASK TITLE="12. add hint how to get part/sub expression" ID="114" ICONINDEX="-1" POS="12" PRIORITY="5" RISK="0" PERCENTDONE="0" COST="0.00000000" CALCCOST="0.00000000" STARTDATE="41824.00000000" STARTDATESTRING="2014-07-04" CREATIONDATE="41824.96760417" CREATIONDATESTRING="2014-07-04T23:13" LASTMOD="41824.96775463" LASTMODSTRING="2014-07-04T23:13" PRIORITYCOLOR="15732480" PRIORITYWEBCOLOR="#000FF0"/>
</TASK>
<TASK TITLE="Misc" ID="27" ICONINDEX="-1" POS="2" PRIORITY="5" RISK="0" PERCENTDONE="0" COST="0.00000000" CALCCOST="0.00000000" STARTDATE="38524.00000000" STARTDATESTRING="2005-06-21" CREATIONDATE="0.00000000" CREATIONDATESTRING="1899-12-30" LASTMOD="40867.62101852" LASTMODSTRING="2011-11-20T14:54" PRIORITYCOLOR="15732480" PRIORITYWEBCOLOR="#000FF0">
<TASK TITLE="add ORACLE_HOME / TNS_ADMIN to trace info" ID="91" ICONINDEX="-1" POS="1" PRIORITY="10" RISK="0" PERCENTDONE="0" COST="0.00000000" CALCCOST="0.00000000" STARTDATE="40853.00000000" STARTDATESTRING="2011-11-06" CREATIONDATE="40853.79399306" CREATIONDATESTRING="2011-11-06T19:03" LASTMOD="41824.81464120" LASTMODSTRING="2014-07-04T19:33" PRIORITYCOLOR="255" PRIORITYWEBCOLOR="#FF0000"/>
<TASK TITLE="null in grid" ID="37" ICONINDEX="-1" COMMENTS="Alexey,

 

Could you please show NULL or whatever you have in settings when option ‘no lob fetch’ is ON? I think checking for NULLs is very cheap. Right now with that option I see &lt;Skipped&gt; even for NULLs in LOB columns.

 

 

Thanks.

SELECT * FROM user_tab_columns WHERE data_type = 'CLOB';

SELECT 1, t.* FROM clob_test t;

INSERT INTO clob_test VALUES('the second column contains NULL', NULL);
COMMIT" POS="2" PRIORITY="5" RISK="0" PERCENTDONE="0" COST="0.00000000" CALCCOST="0.00000000" STARTDATE="39939.00000000" STARTDATESTRING="2009-05-06" CREATIONDATE="39939.00000000" CREATIONDATESTRING="2009-05-06" LASTMOD="40818.43716435" LASTMODSTRING="2011-10-02T10:29" COMMENTSTYPE="PLAIN_TEXT" PRIORITYCOLOR="15732480" PRIORITYWEBCOLOR="#000FF0"/>
<TASK TITLE="Later" ID="101" ICONINDEX="-1" POS="3" PRIORITY="5" RISK="0" PERCENTDONE="0" COST="0.00000000" CALCCOST="0.00000000" STARTDATE="41824.00000000" STARTDATESTRING="2014-07-04" CREATIONDATE="41824.82496528" CREATIONDATESTRING="2014-07-04T19:47" LASTMOD="41824.82501157" LASTMODSTRING="2014-07-04T19:48" PRIORITYCOLOR="15732480" PRIORITYWEBCOLOR="#000FF0">
<TASK TITLE="1097647 Filter for Extract schema ddl" ID="13" ICONINDEX="-1" POS="1" PRIORITY="5" RISK="0" PERCENTDONE="0" COST="0.00000000" CALCCOST="0.00000000" STARTDATE="38524.00000000" STARTDATESTRING="2005-06-21" CREATIONDATE="0.00000000" CREATIONDATESTRING="1899-12-30" LASTMOD="38524.91572917" LASTMODSTRING="2005-06-21T21:58" PRIORITYCOLOR="15732480" PRIORITYWEBCOLOR="#000FF0"/>
<TASK TITLE="1088547 Add SQL File Counter" ID="17" ICONINDEX="-1" POS="2" PRIORITY="3" RISK="0" PERCENTDONE="0" COST="0.00000000" CALCCOST="0.00000000" STARTDATE="38524.00000000" STARTDATESTRING="2005-06-21" CREATIONDATE="0.00000000" CREATIONDATESTRING="1899-12-30" LASTMOD="38524.91611111" LASTMODSTRING="2005-06-21T21:59" PRIORITYCOLOR="15388928" PRIORITYWEBCOLOR="#00D1EA"/>
<TASK TITLE="1108089 cleanup sql statements history" ID="8" ICONINDEX="-1" POS="3" PRIORITY="3" RISK="0" PERCENTDONE="0" COST="0.00000000" CALCCOST="0.00000000" STARTDATE="38524.00000000" STARTDATESTRING="2005-06-21" CREATIONDATE="0.00000000" CREATIONDATESTRING="1899-12-30" LASTMOD="38524.91591435" LASTMODSTRING="2005-06-21T21:58" PRIORITYCOLOR="15388928" PRIORITYWEBCOLOR="#00D1EA"/>
<TASK TITLE="1078872 Datestamp in SaveAs dialog" ID="22" ICONINDEX="-1" POS="4" PRIORITY="3" RISK="0" PERCENTDONE="0" COST="0.00000000" CALCCOST="0.00000000" STARTDATE="38524.00000000" STARTDATESTRING="2005-06-21" CREATIONDATE="0.00000000" CREATIONDATESTRING="1899-12-30" LASTMOD="38524.91604167" LASTMODSTRING="2005-06-21T21:59" PRIORITYCOLOR="15388928" PRIORITYWEBCOLOR="#00D1EA"/>
<TASK TITLE="defult schema for Object List as an attribute of connection" ID="46" ICONINDEX="-1" POS="5" PRIORITY="5" RISK="0" PERCENTDONE="0" COST="0.00000000" CALCCOST="0.00000000" STARTDATE="40800.00000000" STARTDATESTRING="2011-09-14" CREATIONDATE="40800.35266204" CREATIONDATESTRING="2011-09-14T08:27" LASTMOD="40800.35321759" LASTMODSTRING="2011-09-14T08:28" PRIORITYCOLOR="15732480" PRIORITYWEBCOLOR="#000FF0"/>
<TASK TITLE="export in file" ID="34" ICONINDEX="-1" COMMENTS="Pls do not fetch data in full into memory when you save/export it to disk. Can be straight to disk operation with minimal memory use." POS="6" PRIORITY="5" RISK="0" PERCENTDONE="0" COST="0.00000000" CALCCOST="0.00000000" STARTDATE="39939.00000000" STARTDATESTRING="2009-05-06" CREATIONDATE="39939.00000000" CREATIONDATESTRING="2009-05-06" LASTMOD="39939.85675926" LASTMODSTRING="2009-05-06T20:33" COMMENTSTYPE="PLAIN_TEXT" PRIORITYCOLOR="15732480" PRIORITYWEBCOLOR="#000FF0"/>
<TASK TITLE="highlighting too long identifiers" ID="93" ICONINDEX="-1" POS="7" PRIORITY="5" RISK="0" PERCENTDONE="0" COST="0.00000000" CALCCOST="0.00000000" STARTDATE="40867.00000000" STARTDATESTRING="2011-11-20" CREATIONDATE="40867.62163194" CREATIONDATESTRING="2011-11-20T14:55" LASTMOD="40867.62174769" LASTMODSTRING="2011-11-20T14:55" PRIORITYCOLOR="15732480" PRIORITYWEBCOLOR="#000FF0"/>
</TASK>
</TASK>
<TASK TITLE="SQLT" ID="1" ICONINDEX="-1" POS="3" PRIORITY="5" RISK="0" PERCENTDONE="0" CALCPERCENTDONE="11" COST="0.00000000" CALCCOST="0.00000000" STARTDATE="38524.00000000" STARTDATESTRING="2005-06-21" CREATIONDATE="0.00000000" CREATIONDATESTRING="1899-12-30" LASTMOD="40822.73033565" LASTMODSTRING="2011-10-06T17:31" PRIORITYCOLOR="15732480" PRIORITYWEBCOLOR="#000FF0">
<TASK TITLE="SQL Console" ID="26" ICONINDEX="-1" POS="1" PRIORITY="7" RISK="0" PERCENTDONE="0" CALCPERCENTDONE="17" COST="0.00000000" CALCCOST="0.00000000" STARTDATE="38524.00000000" STARTDATESTRING="2005-06-21" CREATIONDATE="0.00000000" CREATIONDATESTRING="1899-12-30" LASTMOD="38524.91219907" LASTMODSTRING="2005-06-21T21:53" PRIORITYCOLOR="16122042" PRIORITYWEBCOLOR="#BA00F6">
<TASK TITLE="show abort dialog and re-paint screen after halt on error and before continue" ID="89" ICONINDEX="-1" POS="1" PRIORITY="7" RISK="0" PERCENTDONE="0" COST="0.00000000" CALCCOST="0.00000000" STARTDATE="40847.00000000" STARTDATESTRING="2011-10-31" CREATIONDATE="40847.45460648" CREATIONDATESTRING="2011-10-31T10:54" LASTMOD="40850.95293981" LASTMODSTRING="2011-11-03T22:52" PRIORITYCOLOR="16122042" PRIORITYWEBCOLOR="#BA00F6"/>
<TASK TITLE="1160406 Queries in background mode" ID="5" ICONINDEX="-1" POS="2" PRIORITY="5" RISK="0" PERCENTDONE="0" COST="0.00000000" CALCCOST="0.00000000" STARTDATE="38524.00000000" STARTDATESTRING="2005-06-21" CREATIONDATE="0.00000000" CREATIONDATESTRING="1899-12-30" LASTMOD="38524.90398148" LASTMODSTRING="2005-06-21T21:41" PRIORITYCOLOR="15732480" PRIORITYWEBCOLOR="#000FF0"/>
<TASK TITLE="1108077 single statement execution" ID="10" ICONINDEX="-1" POS="3" PRIORITY="5" RISK="0" PERCENTDONE="0" COST="0.00000000" CALCCOST="0.00000000" STARTDATE="38524.00000000" STARTDATESTRING="2005-06-21" CREATIONDATE="0.00000000" CREATIONDATESTRING="1899-12-30" LASTMOD="38524.91530093" LASTMODSTRING="2005-06-21T21:58" PRIORITYCOLOR="15732480" PRIORITYWEBCOLOR="#000FF0"/>
<TASK TITLE="1159681 Breakpoint / Pause command" ID="6" ICONINDEX="-1" POS="4" PRIORITY="3" RISK="0" PERCENTDONE="0" COST="0.00000000" CALCCOST="0.00000000" STARTDATE="38524.00000000" STARTDATESTRING="2005-06-21" CREATIONDATE="0.00000000" CREATIONDATESTRING="1899-12-30" LASTMOD="38524.91557870" LASTMODSTRING="2005-06-21T21:58" PRIORITYCOLOR="15388928" PRIORITYWEBCOLOR="#00D1EA"/>
<TASK TITLE="; at the and of SQL*plus command" ID="54" ICONINDEX="-1" COMMENTS="var i number;

connect user/password@db;" POS="5" PRIORITY="5" RISK="0" PERCENTDONE="0" COST="0.00000000" CALCCOST="0.00000000" STARTDATE="40801.00000000" STARTDATESTRING="2011-09-15" CREATIONDATE="40801.81023148" CREATIONDATESTRING="2011-09-15T19:26" LASTMOD="40801.81287037" LASTMODSTRING="2011-09-15T19:30" COMMENTSTYPE="PLAIN_TEXT" PRIORITYCOLOR="15732480" PRIORITYWEBCOLOR="#000FF0"/>
<TASK TITLE="Run a procedure with sys_refcursor output" ID="62" ICONINDEX="-1" COMMENTS="http://sqltools.net/cgi-bin/yabb2/YaBB.pl?num=1292848046" POS="6" PRIORITY="5" RISK="0" PERCENTDONE="100" CALCPERCENTDONE="100" COST="0.00000000" CALCCOST="0.00000000" DONEDATE="41824.80589120" DONEDATESTRING="2014-07-04T19:20" STARTDATE="40802.00000000" STARTDATESTRING="2011-09-16" CREATIONDATE="40802.86064815" CREATIONDATESTRING="2011-09-16T20:39" LASTMOD="41824.80589120" LASTMODSTRING="2014-07-04T19:20" COMMENTSTYPE="PLAIN_TEXT" TEXTCOLOR="8421504" TEXTWEBCOLOR="#808080" PRIORITYCOLOR="57630" PRIORITYWEBCOLOR="#1EE100"/>
</TASK>
<TASK TITLE="DDL reverse-engineering" ID="29" ICONINDEX="-1" POS="2" PRIORITY="8" RISK="0" PERCENTDONE="0" COST="0.00000000" CALCCOST="0.00000000" STARTDATE="38524.00000000" STARTDATESTRING="2005-06-21" CREATIONDATE="0.00000000" CREATIONDATESTRING="1899-12-30" LASTMOD="38524.91233796" LASTMODSTRING="2005-06-21T21:53" PRIORITYCOLOR="13435129" PRIORITYWEBCOLOR="#F900CD">
<TASK TITLE="External tables" ID="96" ICONINDEX="-1" COMMENTS="http://www.sqltools.net/cgi-bin/yabb25/YaBB.pl?num=1403599641/0#0" POS="1" PRIORITY="8" RISK="0" PERCENTDONE="0" COST="0.00000000" CALCCOST="0.00000000" STARTDATE="41824.00000000" STARTDATESTRING="2014-07-04" CREATIONDATE="41824.81922454" CREATIONDATESTRING="2014-07-04T19:39" LASTMOD="41824.82255787" LASTMODSTRING="2014-07-04T19:44" COMMENTSTYPE="PLAIN_TEXT" PRIORITYCOLOR="13435129" PRIORITYWEBCOLOR="#F900CD"/>
<TASK TITLE="impove DDL for hash partitioned table" ID="67" ICONINDEX="-1" COMMENTS="Oracle expands &quot;PARTITIONS 8 &quot; to:

  (
    PARTITION sys_p421,
    PARTITION sys_p422,
    PARTITION sys_p423,
    PARTITION sys_p424,
    PARTITION sys_p425,
    PARTITION sys_p426,
    PARTITION sys_p427,
    PARTITION sys_p428
  )

To get back ô short notation, check if partition names are generated then use PARTITIONS N 

SELECT subobject_name, generated FROM user_objects WHERE object_name = 'PT_HASH';" POS="2" PRIORITY="9" RISK="0" PERCENTDONE="0" COST="0.00000000" CALCCOST="0.00000000" STARTDATE="40808.00000000" STARTDATESTRING="2011-09-22" CREATIONDATE="40808.84417824" CREATIONDATESTRING="2011-09-22T20:15" LASTMOD="41824.82265046" LASTMODSTRING="2014-07-04T19:44" COMMENTSTYPE="PLAIN_TEXT" PRIORITYCOLOR="6815996" PRIORITYWEBCOLOR="#FC0068"/>
<TASK TITLE="Later" ID="98" ICONINDEX="-1" POS="3" PRIORITY="5" RISK="0" PERCENTDONE="0" COST="0.00000000" CALCCOST="0.00000000" STARTDATE="41824.00000000" STARTDATESTRING="2014-07-04" CREATIONDATE="41824.82041667" CREATIONDATESTRING="2014-07-04T19:41" LASTMOD="41824.82055556" LASTMODSTRING="2014-07-04T19:41" PRIORITYCOLOR="15732480" PRIORITYWEBCOLOR="#000FF0">
<TASK TITLE="do local sorting for partition list" ID="82" ICONINDEX="-1" POS="1" PRIORITY="5" RISK="0" PERCENTDONE="0" COST="0.00000000" CALCCOST="0.00000000" STARTDATE="40830.00000000" STARTDATESTRING="2011-10-14" CREATIONDATE="40830.87930556" CREATIONDATESTRING="2011-10-14T21:06" LASTMOD="40830.87940972" LASTMODSTRING="2011-10-14T21:06" PRIORITYCOLOR="15732480" PRIORITYWEBCOLOR="#000FF0"/>
<TASK TITLE="1095550 Generate script for Materialized views" ID="16" ICONINDEX="-1" POS="2" PRIORITY="5" RISK="0" PERCENTDONE="0" COST="0.00000000" CALCCOST="0.00000000" STARTDATE="38524.00000000" STARTDATESTRING="2005-06-21" CREATIONDATE="0.00000000" CREATIONDATESTRING="1899-12-30" LASTMOD="38524.91502315" LASTMODSTRING="2005-06-21T21:57" PRIORITYCOLOR="15732480" PRIORITYWEBCOLOR="#000FF0"/>
<TASK TITLE="1096327 Extract Schema package in one file" ID="15" ICONINDEX="-1" POS="3" PRIORITY="3" RISK="0" PERCENTDONE="0" COST="0.00000000" CALCCOST="0.00000000" STARTDATE="38524.00000000" STARTDATESTRING="2005-06-21" CREATIONDATE="0.00000000" CREATIONDATESTRING="1899-12-30" LASTMOD="38524.91508102" LASTMODSTRING="2005-06-21T21:57" PRIORITYCOLOR="15388928" PRIORITYWEBCOLOR="#00D1EA"/>
<TASK TITLE="1119109 File Extentions for &quot;Extract Schema DDL&quot;" ID="7" ICONINDEX="-1" POS="4" PRIORITY="3" RISK="0" PERCENTDONE="0" COST="0.00000000" CALCCOST="0.00000000" STARTDATE="38524.00000000" STARTDATESTRING="2005-06-21" CREATIONDATE="0.00000000" CREATIONDATESTRING="1899-12-30" LASTMOD="38524.91515046" LASTMODSTRING="2005-06-21T21:57" PRIORITYCOLOR="15388928" PRIORITYWEBCOLOR="#00D1EA"/>
<TASK TITLE="matview" ID="38" ICONINDEX="-1" COMMENTS="Looks like reverse engineering by Ctrl-F12 does not work for materialized views. Object browser shows them as regular tables without any clue that it’s not exactly the table.

 

Please make a post about this problem in the forum:

            http://www.sqltools.net/cgi-bin/yabb2/YaBB.pl

We need the stack trace (see below) and short description

what were you doing when this problem occurred (optional).

 

Invalid object type

 

Program: SQLTools 1.4.2 RC3 (for trouble-shooting)

Location: .\SQLWorksheet\SQLWorksheetDoc.cpp(1095).

Platform: MS Windows XP Professional, Service Pack 2 (Build 2600)

COMCTL32.DLL: 6.0.2900.2180

OCI.DLL: 10.2.0.1.0

Connected to: 10.2.0.2.0

 

Stack at the catch point:

0x7c90eb94                   KiFastSystemCallRet() + 0" POS="5" PRIORITY="5" RISK="0" PERCENTDONE="0" COST="0.00000000" CALCCOST="0.00000000" STARTDATE="39939.00000000" STARTDATESTRING="2009-05-06" CREATIONDATE="39939.00000000" CREATIONDATESTRING="2009-05-06" LASTMOD="39939.86583333" LASTMODSTRING="2009-05-06T20:46" COMMENTSTYPE="PLAIN_TEXT" PRIORITYCOLOR="15732480" PRIORITYWEBCOLOR="#000FF0"/>
<TASK TITLE="Unwind dependencies algorithm error!" ID="39" ICONINDEX="-1" COMMENTS="Hello - I received the below error when trying to Extract Schema DDL.  Can you please help?
 
Unwind dependencies algorithm error!
Program: SQLTools 1.4.1 build 72 (for trouble-shooting)
Location: .\Tools\ExtractSchemaDlg.cpp(462).
Platform: MS Windows XP Professional, Service Pack 2 (Build 2600)
COMCTL32.DLL: 6.0.2900.2180
OCI.DLL: 9.2.0.1.0
Connected to: 9.2.0.5.0
Stack at the catch point:
0x7c90eb94  KiFastSystemCallRet() + 0" POS="6" PRIORITY="5" RISK="0" PERCENTDONE="0" COST="0.00000000" CALCCOST="0.00000000" STARTDATE="39939.00000000" STARTDATESTRING="2009-05-06" CREATIONDATE="39939.00000000" CREATIONDATESTRING="2009-05-06" LASTMOD="39939.87048611" LASTMODSTRING="2009-05-06T20:53" COMMENTSTYPE="PLAIN_TEXT" PRIORITYCOLOR="15732480" PRIORITYWEBCOLOR="#000FF0"/>
</TASK>
</TASK>
<TASK TITLE="Quick Viewer" ID="28" ICONINDEX="-1" POS="3" PRIORITY="5" RISK="0" PERCENTDONE="0" COST="0.00000000" CALCCOST="0.00000000" STARTDATE="38524.00000000" STARTDATESTRING="2005-06-21" CREATIONDATE="0.00000000" CREATIONDATESTRING="1899-12-30" LASTMOD="38524.91055556" LASTMODSTRING="2005-06-21T21:51" PRIORITYCOLOR="15732480" PRIORITYWEBCOLOR="#000FF0"/>
<TASK TITLE="Borrow SQLTools++ feastures:" ID="42" ICONINDEX="-1" POS="4" PRIORITY="5" RISK="0" PERCENTDONE="0" CALCPERCENTDONE="50" COST="0.00000000" CALCCOST="0.00000000" STARTDATE="40800.00000000" STARTDATESTRING="2011-09-14" CREATIONDATE="40800.33825231" CREATIONDATESTRING="2011-09-14T08:07" LASTMOD="40800.33851852" LASTMODSTRING="2011-09-14T08:07" PRIORITYCOLOR="15732480" PRIORITYWEBCOLOR="#000FF0">
<TASK TITLE="DBMS_XPLAN.DISPLAY" ID="44" ICONINDEX="-1" POS="1" PRIORITY="0" RISK="0" PERCENTDONE="100" CALCPERCENTDONE="100" COST="0.00000000" CALCCOST="0.00000000" DONEDATE="41824.80685185" DONEDATESTRING="2014-07-04T19:21" STARTDATE="40800.00000000" STARTDATESTRING="2011-09-14" CREATIONDATE="40800.34837963" CREATIONDATESTRING="2011-09-14T08:21" LASTMOD="41824.80685185" LASTMODSTRING="2014-07-04T19:21" TEXTCOLOR="8421504" TEXTWEBCOLOR="#808080" PRIORITYCOLOR="57630" PRIORITYWEBCOLOR="#1EE100"/>
<TASK TITLE="Later" ID="99" ICONINDEX="-1" POS="2" PRIORITY="5" RISK="0" PERCENTDONE="0" COST="0.00000000" CALCCOST="0.00000000" STARTDATE="41824.00000000" STARTDATESTRING="2014-07-04" CREATIONDATE="41824.82278935" CREATIONDATESTRING="2014-07-04T19:44" LASTMOD="41824.82289352" LASTMODSTRING="2014-07-04T19:44" PRIORITYCOLOR="15732480" PRIORITYWEBCOLOR="#000FF0">
<TASK TITLE="DBMS_XPLAN.DISPLAY_CURSOR" ID="43" ICONINDEX="-1" POS="1" PRIORITY="5" RISK="0" PERCENTDONE="0" COST="0.00000000" CALCCOST="0.00000000" STARTDATE="40800.00000000" STARTDATESTRING="2011-09-14" CREATIONDATE="40800.33856481" CREATIONDATESTRING="2011-09-14T08:07" LASTMOD="40800.35023148" LASTMODSTRING="2011-09-14T08:24" PRIORITYCOLOR="15732480" PRIORITYWEBCOLOR="#000FF0"/>
</TASK>
</TASK>
<TASK TITLE="General Bugs" ID="30" ICONINDEX="-1" POS="5" PRIORITY="8" RISK="0" PERCENTDONE="0" COST="0.00000000" CALCCOST="0.00000000" STARTDATE="38524.00000000" STARTDATESTRING="2005-06-21" CREATIONDATE="0.00000000" CREATIONDATESTRING="1899-12-30" LASTMOD="40822.72937500" LASTMODSTRING="2011-10-06T17:30" PRIORITYCOLOR="13435129" PRIORITYWEBCOLOR="#F900CD"/>
<TASK TITLE="General Improvements" ID="77" ICONINDEX="-1" POS="6" PRIORITY="5" RISK="0" PERCENTDONE="0" COST="0.00000000" CALCCOST="0.00000000" STARTDATE="40822.00000000" STARTDATESTRING="2011-10-06" CREATIONDATE="40822.73393519" CREATIONDATESTRING="2011-10-06T17:36" LASTMOD="40822.73410880" LASTMODSTRING="2011-10-06T17:37" PRIORITYCOLOR="15732480" PRIORITYWEBCOLOR="#000FF0">
<TASK TITLE="cleanup cancel flag on connect/disconnect" ID="79" ICONINDEX="-1" POS="1" PRIORITY="5" RISK="0" PERCENTDONE="0" COST="0.00000000" CALCCOST="0.00000000" STARTDATE="40822.00000000" STARTDATESTRING="2011-10-06" CREATIONDATE="40822.73534722" CREATIONDATESTRING="2011-10-06T17:38" LASTMOD="40822.73537037" LASTMODSTRING="2011-10-06T17:38" PRIORITYCOLOR="15732480" PRIORITYWEBCOLOR="#000FF0"/>
</TASK>
</TASK>
<TASK TITLE="OE" ID="47" ICONINDEX="-1" POS="4" PRIORITY="5" RISK="0" PERCENTDONE="0" CALCPERCENTDONE="12" COST="0.00000000" CALCCOST="0.00000000" STARTDATE="40800.00000000" STARTDATESTRING="2011-09-14" CREATIONDATE="40800.42305556" CREATIONDATESTRING="2011-09-14T10:09" LASTMOD="40800.42313657" LASTMODSTRING="2011-09-14T10:09" PRIORITYCOLOR="15732480" PRIORITYWEBCOLOR="#000FF0">
<TASK TITLE="Save workspace" ID="65" ICONINDEX="-1" COMMENTS="http://www.sqltools.net/cgi-bin/yabb25/YaBB.pl?board=SQLTools

autosave before execution. sve new files in temp folder " POS="1" PRIORITY="8" RISK="0" PERCENTDONE="0" COST="0.00000000" CALCCOST="0.00000000" STARTDATE="40807.00000000" STARTDATESTRING="2011-09-21" CREATIONDATE="40807.38850694" CREATIONDATESTRING="2011-09-21T09:19" LASTMOD="41824.82417824" LASTMODSTRING="2014-07-04T19:46" COMMENTSTYPE="PLAIN_TEXT" PRIORITYCOLOR="13435129" PRIORITYWEBCOLOR="#F900CD"/>
<TASK TITLE="comments like in MSVC" ID="75" ICONINDEX="-1" POS="2" PRIORITY="5" RISK="0" PERCENTDONE="0" COST="0.00000000" CALCCOST="0.00000000" STARTDATE="40818.00000000" STARTDATESTRING="2011-10-02" CREATIONDATE="40818.43755787" CREATIONDATESTRING="2011-10-02T10:30" LASTMOD="40818.43781250" LASTMODSTRING="2011-10-02T10:30" PRIORITYCOLOR="15732480" PRIORITYWEBCOLOR="#000FF0"/>
<TASK TITLE="PL/SQL analyzer fails on incomplete types" ID="69" ICONINDEX="-1" POS="3" PRIORITY="5" RISK="0" PERCENTDONE="0" COST="0.00000000" CALCCOST="0.00000000" STARTDATE="40814.00000000" STARTDATESTRING="2011-09-28" CREATIONDATE="40814.88012731" CREATIONDATESTRING="2011-09-28T21:07" LASTMOD="40814.88034722" LASTMODSTRING="2011-09-28T21:07" PRIORITYCOLOR="15732480" PRIORITYWEBCOLOR="#000FF0"/>
<TASK TITLE="PL/SQL analyzer cannot parse table transformer script" ID="85" ICONINDEX="-1" POS="4" PRIORITY="5" RISK="0" PERCENTDONE="100" CALCPERCENTDONE="100" COST="0.00000000" CALCCOST="0.00000000" DONEDATE="41824.80706019" DONEDATESTRING="2014-07-04T19:22" STARTDATE="40843.00000000" STARTDATESTRING="2011-10-27" CREATIONDATE="40843.78552083" CREATIONDATESTRING="2011-10-27T18:51" LASTMOD="41824.80706019" LASTMODSTRING="2014-07-04T19:22" TEXTCOLOR="8421504" TEXTWEBCOLOR="#808080" PRIORITYCOLOR="57630" PRIORITYWEBCOLOR="#1EE100"/>
<TASK TITLE="add high lever error handling in COEDocument::LoadSettingsManager ()" ID="76" ICONINDEX="-1" POS="5" PRIORITY="5" RISK="0" PERCENTDONE="0" COST="0.00000000" CALCCOST="0.00000000" STARTDATE="40821.00000000" STARTDATESTRING="2011-10-05" CREATIONDATE="40821.78314815" CREATIONDATESTRING="2011-10-05T18:47" LASTMOD="40821.78366898" LASTMODSTRING="2011-10-05T18:48" PRIORITYCOLOR="15732480" PRIORITYWEBCOLOR="#000FF0"/>
<TASK TITLE="End-of-line marks and columns" ID="61" ICONINDEX="-1" COMMENTS="http://sqltools.net/cgi-bin/yabb2/YaBB.pl?num=1253371188

Hi Alexis
This is my list of wishes for OpenEditor:
 
1. When the &quot;Visible spaces&quot; is activated mark the end-of-line:
    Maybe use the ascii 182 (in Windows code page 1252),
    or draw a small image with &quot;CR&quot; if carriage_return (ascii 13) and/or &quot;LF&quot; if line_feed (ascii 10)
    (I saw this on NotePad++)
 
2. A fast way to mark/un-mark columns using a double-click on ruler
 
3. A way to save the columns settings
(I use a lot of files with fixed-record length) " POS="6" PRIORITY="5" RISK="0" PERCENTDONE="0" COST="0.00000000" CALCCOST="0.00000000" STARTDATE="40802.00000000" STARTDATESTRING="2011-09-16" CREATIONDATE="40802.84622685" CREATIONDATESTRING="2011-09-16T20:18" LASTMOD="40802.84726852" LASTMODSTRING="2011-09-16T20:20" COMMENTSTYPE="PLAIN_TEXT" PRIORITYCOLOR="15732480" PRIORITYWEBCOLOR="#000FF0"/>
<TASK TITLE="m_Rulers[1].m_Topmost = max(0, m_nFistHighlightedLine - 1);" ID="86" ICONINDEX="-1" POS="7" PRIORITY="10" RISK="0" PERCENTDONE="0" COST="0.00000000" CALCCOST="0.00000000" STARTDATE="40843.00000000" STARTDATESTRING="2011-10-27" CREATIONDATE="40843.78615741" CREATIONDATESTRING="2011-10-27T18:52" LASTMOD="40843.78625000" LASTMODSTRING="2011-10-27T18:52" PRIORITYCOLOR="255" PRIORITYWEBCOLOR="#FF0000"/>
<TASK TITLE="Later" ID="100" ICONINDEX="-1" POS="8" PRIORITY="5" RISK="0" PERCENTDONE="0" COST="0.00000000" CALCCOST="0.00000000" STARTDATE="41824.00000000" STARTDATESTRING="2014-07-04" CREATIONDATE="41824.82444444" CREATIONDATESTRING="2014-07-04T19:47" LASTMOD="41824.82451389" LASTMODSTRING="2014-07-04T19:47" PRIORITYCOLOR="15732480" PRIORITYWEBCOLOR="#000FF0"/>
</TASK>
<TASK TITLE="Research &amp; Borrow" ID="57" ICONINDEX="-1" POS="5" PRIORITY="5" RISK="0" PERCENTDONE="0" COST="0.00000000" CALCCOST="0.00000000" STARTDATE="40802.00000000" STARTDATESTRING="2011-09-16" CREATIONDATE="40802.84199074" CREATIONDATESTRING="2011-09-16T20:12" LASTMOD="40802.86739583" LASTMODSTRING="2011-09-16T20:49" PRIORITYCOLOR="15732480" PRIORITYWEBCOLOR="#000FF0">
<TASK TITLE="http://sourceforge.net/projects/emeraldeditor/" ID="58" ICONINDEX="-1" POS="1" PRIORITY="5" RISK="0" PERCENTDONE="0" COST="0.00000000" CALCCOST="0.00000000" STARTDATE="40802.00000000" STARTDATESTRING="2011-09-16" CREATIONDATE="40802.84240741" CREATIONDATESTRING="2011-09-16T20:13" LASTMOD="40802.84244213" LASTMODSTRING="2011-09-16T20:13" PRIORITYCOLOR="15732480" PRIORITYWEBCOLOR="#000FF0"/>
<TASK TITLE="http://www.sqlinform.com/free_online_sw.html" ID="78" ICONINDEX="-1" POS="2" PRIORITY="5" RISK="0" PERCENTDONE="0" COST="0.00000000" CALCCOST="0.00000000" STARTDATE="40822.00000000" STARTDATESTRING="2011-10-06" CREATIONDATE="40822.73502315" CREATIONDATESTRING="2011-10-06T17:38" LASTMOD="40822.73505787" LASTMODSTRING="2011-10-06T17:38" PRIORITYCOLOR="15732480" PRIORITYWEBCOLOR="#000FF0"/>
<TASK TITLE="http://orclib.sourceforge.net/projects/" ID="83" ICONINDEX="-1" POS="3" PRIORITY="9" RISK="0" PERCENTDONE="0" COST="0.00000000" CALCCOST="0.00000000" STARTDATE="40836.00000000" STARTDATESTRING="2011-10-20" CREATIONDATE="40836.85339120" CREATIONDATESTRING="2011-10-20T20:28" LASTMOD="40836.85385417" LASTMODSTRING="2011-10-20T20:29" PRIORITYCOLOR="6815996" PRIORITYWEBCOLOR="#FC0068"/>
<TASK TITLE="https://sourceforge.net/projects/orbada/" ID="88" ICONINDEX="-1" POS="4" PRIORITY="5" RISK="0" PERCENTDONE="0" COST="0.00000000" CALCCOST="0.00000000" STARTDATE="40843.00000000" STARTDATESTRING="2011-10-27" CREATIONDATE="40843.79164352" CREATIONDATESTRING="2011-10-27T18:59" LASTMOD="40843.79170139" LASTMODSTRING="2011-10-27T19:00" PRIORITYCOLOR="15732480" PRIORITYWEBCOLOR="#000FF0"/>
</TASK>
<TASK TITLE="Later" ID="2" ICONINDEX="-1" POS="6" PRIORITY="-2" RISK="0" PERCENTDONE="0" COST="0.00000000" CALCCOST="0.00000000" STARTDATE="38524.00000000" STARTDATESTRING="2005-06-21" CREATIONDATE="0.00000000" CREATIONDATESTRING="1899-12-30" LASTMOD="40822.73061343" LASTMODSTRING="2011-10-06T17:32" PRIORITYCOLOR="0" PRIORITYWEBCOLOR="#000000"/>
</TODOLIST>
